odins_spear/__init__.py
odins_spear/api.py
odins_spear/exceptions.py
odins_spear/reporter.py
odins_spear/requester.py
odins_spear/scripter.py
odins_spear/endpoints/__init__.py
odins_spear/endpoints/administrators.py
odins_spear/endpoints/alternate_numbers.py
odins_spear/endpoints/announcements.py
odins_spear/endpoints/authentication.py
odins_spear/endpoints/auto_attendant.py
odins_spear/endpoints/base_endpoint.py
odins_spear/endpoints/call_centers.py
odins_spear/endpoints/call_forwarding_always.py
odins_spear/endpoints/call_forwarding_busy.py
odins_spear/endpoints/call_forwarding_no_answer.py
odins_spear/endpoints/call_forwarding_not_reachable.py
odins_spear/endpoints/call_fowarding_selective.py
odins_spear/endpoints/call_pickup.py
odins_spear/endpoints/call_processing_policies.py
odins_spear/endpoints/call_records.py
odins_spear/endpoints/devices.py
odins_spear/endpoints/dns.py
odins_spear/endpoints/do_not_disturb.py
odins_spear/endpoints/emergency_zones.py
odins_spear/endpoints/groups.py
odins_spear/endpoints/hunt_groups.py
odins_spear/endpoints/password_generate.py
odins_spear/endpoints/registration.py
odins_spear/endpoints/reports.py
odins_spear/endpoints/schedules.py
odins_spear/endpoints/service_providers.py
odins_spear/endpoints/services.py
odins_spear/endpoints/session.py
odins_spear/endpoints/shared_call_appearance.py
odins_spear/endpoints/trunk_groups.py
odins_spear/endpoints/users.py
odins_spear/reports/__init__.py
odins_spear/reports/call_flow.py
odins_spear/reports/group_users_call_statistics.py
odins_spear/reports/user_registration_report.py
odins_spear/reports/report_utils/__init__.py
odins_spear/reports/report_utils/graphviz_module.py
odins_spear/reports/report_utils/parsing.py
odins_spear/reports/report_utils/report_entities.py
odins_spear/scripts/__init__.py
odins_spear/scripts/bulk_password_reset.py
odins_spear/scripts/find_alias.py
odins_spear/scripts/group_audit.py
odins_spear/scripts/locate_free_extension.py
odins_spear/scripts/move_numbers.py
odins_spear-2.3.0.dist-info/METADATA
odins_spear-2.3.0.dist-info/WHEEL
odins_spear-2.3.0.dist-info/top_level.txt
odins_spear-2.3.0.dist-info/RECORD
