Metadata-Version: 2.4
Name: odins-spear
Version: 2.3.0
Summary: Python package for Odin's API to build and manage Broadworks installations.
Author-email: Jordan Prescott <jordan@minimalmind.io>
License: MIT License
Keywords: broadworks,odin,api,telephony,voip
Classifier: Development Status :: 4 - Beta
Classifier: Intended Audience :: Developers
Classifier: License :: OSI Approved :: MIT License
Classifier: Programming Language :: Python
Classifier: Programming Language :: Python :: 3
Classifier: Programming Language :: Python :: 3.9
Classifier: Programming Language :: Python :: 3.10
Classifier: Programming Language :: Python :: 3.12
Classifier: Operating System :: OS Independent
Classifier: Topic :: Software Development :: Libraries
Classifier: Topic :: Utilities
Requires-Python: <3.13,>=3.9
Requires-Dist: graphviz>=0.20.3
Requires-Dist: openpyxl>=3.1.5
Requires-Dist: pandas>=2.2.3
Requires-Dist: ratelimit>=2.2.1
Requires-Dist: requests>=2.32.3
